ibmseti/__info__.py
ibmseti/__init__.py
ibmseti/compamp.py
ibmseti/constants.py
ibmseti/dsp.py
ibmseti/features.py
ibmseti-2.0.0.dist-info/DESCRIPTION.rst
ibmseti-2.0.0.dist-info/METADATA
ibmseti-2.0.0.dist-info/RECORD
ibmseti-2.0.0.dist-info/WHEEL
ibmseti-2.0.0.dist-info/metadata.json
ibmseti-2.0.0.dist-info/top_level.txt
