Metadata-Version: 2.0
Name: ibmseti
Version: 2.0.0
Summary: SETI ATA data analysis tools
Home-page: https://github.com/ibm-watson-data-lab/ibmseti
Author: gadamc
Author-email: adamcox@us.ibm.com
License: UNKNOWN
Platform: UNKNOWN
Classifier: Intended Audience :: Developers
Classifier: Natural Language :: English
Classifier: License :: OSI Approved :: Apache Software License
Classifier: Topic :: Software Development :: Libraries
Classifier: Development Status :: 5 - Production/Stable
Classifier: Programming Language :: Python
Classifier: Programming Language :: Python :: 2
Classifier: Programming Language :: Python :: 2.7
Classifier: Programming Language :: Python :: 3
Classifier: Programming Language :: Python :: 3.6
Requires-Dist: numpy (>=1.10)
Requires-Dist: scipy (>=0.14.0)
Requires-Dist: six (>=1.10.0)
